mrfmsim/__init__.py
mrfmsim/component/__init__.py
mrfmsim/component/base.py
mrfmsim/component/cantilever.py
mrfmsim/component/cylindermagnet.py
mrfmsim/component/grid.py
mrfmsim/component/magnet.py
mrfmsim/component/sample.py
mrfmsim/experiment/__init__.py
mrfmsim/experiment/cermitarp.py
mrfmsim/experiment/cermitesr.py
mrfmsim/experiment/cermitsinglespin.py
mrfmsim/experiment/cermittd.py
mrfmsim/experiment/ibmcyclic.py
mrfmsim/experiment/stdelements.py
mrfmsim/formula/__init__.py
mrfmsim/formula/field.py
mrfmsim/formula/magnetization.py
mrfmsim/formula/math.py
mrfmsim/formula/misc.py
mrfmsim/formula/polarization.py
mrfmsim/graph.py
mrfmsim/group.py
mrfmsim/model.py
mrfmsim/modifier.py
mrfmsim/node.py
mrfmsim-0.4.1.dist-info/LICENSE
mrfmsim-0.4.1.dist-info/METADATA
mrfmsim-0.4.1.dist-info/WHEEL
mrfmsim-0.4.1.dist-info/RECORD
