Metadata-Version: 2.1
Name: mrfmsim
Version: 0.4.1
Summary: Simulate magnetic resonance force microscopy experiments.
Home-page: https://www.github.com/Marohn-Group/mrfmsim
Author: Peter Sun
Author-email: hs859@cornell.edu
Maintainer: Peter Sun
Maintainer-email: hs859@cornell.edu
Requires-Python: >=3.10
Classifier: Development Status :: 4 - Beta
Classifier: Intended Audience :: Developers
Classifier: Programming Language :: Python :: 3
Classifier: Programming Language :: Python :: 3.10
Classifier: Programming Language :: Python :: 3.11
Classifier: Topic :: Scientific/Engineering
Classifier: Topic :: Software Development :: Libraries :: Python Modules
Provides-Extra: docs
Provides-Extra: test
Requires-Dist: mmodel (>=0.9.0)
Requires-Dist: nbsphinx (==0.9.6) ; extra == "docs"
Requires-Dist: numba (>=0.60.0)
Requires-Dist: numpy (>=1.26.4)
Requires-Dist: pydata-sphinx-theme (==0.16.1) ; extra == "docs"
Requires-Dist: pytest (>=7.1.1) ; extra == "test" or extra == "docs"
Requires-Dist: pytest-cov (>=4.0.0) ; extra == "test"
Requires-Dist: pytest-mock (>=3.4.0)
Requires-Dist: scipy (>=1.14.1)
Requires-Dist: sphinx (==8.1.3) ; extra == "docs"
Requires-Dist: sphinx-book-theme (==1.1.3) ; extra == "docs"
Requires-Dist: tox (>=3.25.0) ; extra == "test"
Requires-Dist: tox-conda (>=0.9.2)
Project-URL: Repository, https://www.github.com/Marohn-Group/mrfmsim
